medjc09/__init__.py
medjc09/command.py
medjc09/medjc09.py
medjc09_hub_python-0.4.0.dist-info/METADATA
medjc09_hub_python-0.4.0.dist-info/WHEEL
medjc09_hub_python-0.4.0.dist-info/licenses/LICENSE
medjc09_hub_python-0.4.0.dist-info/RECORD
