Metadata-Version: 2.3
Name: medjc09-hub-python
Version: 0.4.0
Summary: Python library for medjc09 hub
Author-email: OctSquid <pqvs6k96@s.okayama-u.ac.jp>
License: MIT
Requires-Python: <=3.12,>=3.8
Requires-Dist: asyncio>=3.4.3
Requires-Dist: cobs>=1.2.1
Requires-Dist: pyserial-asyncio>=0.6
Requires-Dist: python-dotenv>=1.0.1
